certbot_dns_subdomain_provider/__init__.py
certbot_dns_subdomain_provider/_internal/__init__.py
certbot_dns_subdomain_provider/_internal/dns_subdomain_provider.py
certbot_dns_subdomain_provider-1.0.2.dist-info/LICENSE.txt
certbot_dns_subdomain_provider-1.0.2.dist-info/METADATA
certbot_dns_subdomain_provider-1.0.2.dist-info/WHEEL
certbot_dns_subdomain_provider-1.0.2.dist-info/entry_points.txt
certbot_dns_subdomain_provider-1.0.2.dist-info/top_level.txt
certbot_dns_subdomain_provider-1.0.2.dist-info/RECORD
