Metadata-Version: 2.1
Name: certbot-dns-subdomain-provider
Version: 1.0.2
Summary: Subdomain Provider DNS Authenticator plugin for Certbot
Home-page: https://github.com/tugrul/certbot-dns-subdomain-provider
Author: Certbot Project
Author-email: tugrultopuz@gmail.com
License: Apache License 2.0
Platform: UNKNOWN
Classifier: Development Status :: 5 - Production/Stable
Classifier: Environment :: Plugins
Classifier: Intended Audience :: System Administrators
Classifier: License :: OSI Approved :: Apache Software License
Classifier: Operating System :: POSIX :: Linux
Classifier: Programming Language :: Python
Classifier: Programming Language :: Python :: 3
Classifier: Programming Language :: Python :: 3.6
Classifier: Programming Language :: Python :: 3.7
Classifier: Programming Language :: Python :: 3.8
Classifier: Programming Language :: Python :: 3.9
Classifier: Topic :: Internet :: WWW/HTTP
Classifier: Topic :: Security
Classifier: Topic :: System :: Installation/Setup
Classifier: Topic :: System :: Networking
Classifier: Topic :: System :: Systems Administration
Classifier: Topic :: Utilities
Requires-Python: >=3.6
Requires-Dist: acme (>=0.29.0)
Requires-Dist: certbot (>=1.1.0)
Requires-Dist: requests
Requires-Dist: setuptools (>=39.0.1)
Requires-Dist: zope.interface
